gpl/__init__.py
gpl/train.py
gpl/toolkit/__init__.py
gpl/toolkit/beir.py
gpl/toolkit/dataset.py
gpl/toolkit/evaluation.py
gpl/toolkit/log.py
gpl/toolkit/loss.py
gpl/toolkit/mine.py
gpl/toolkit/mnrl.py
gpl/toolkit/pl.py
gpl/toolkit/qgen.py
gpl/toolkit/reformat.py
gpl/toolkit/rescale.py
gpl/toolkit/resize.py
gpl/toolkit/sbert.py
gpl-0.1.4.dist-info/LICENSE
gpl-0.1.4.dist-info/METADATA
gpl-0.1.4.dist-info/WHEEL
gpl-0.1.4.dist-info/top_level.txt
gpl-0.1.4.dist-info/RECORD
