Metadata-Version: 2.1
Name: gpl
Version: 0.1.4
Summary: GPL is an unsupervised domain adaptation method for training dense retrievers. It is based on query generation and pseudo labeling with powerful cross-encoders. To train a domain-adapted model, it needs only the unlabeled target corpus and can achieve significant improvement over zero-shot models.
Home-page: https://github.com/UKPLab/gpl
Author: Kexin Wang
Author-email: kexin.wang.2049@gmail.com
License: UNKNOWN
Project-URL: Bug Tracker, https://github.com/UKPLab/gpl/issues
Platform: UNKNOWN
Classifier: Programming Language :: Python :: 3
Classifier: License :: OSI Approved :: Apache Software License
Classifier: Operating System :: OS Independent
Requires-Python: >=3.6
License-File: LICENSE
Requires-Dist: beir
Requires-Dist: easy-elasticsearch (>=0.0.9)
Requires-Dist: protobuf
Requires-Dist: pytest
